sktalk/__init__.py
sktalk/cli.py
sktalk/sktalk.py
sktalk-0.0.400.dist-info/AUTHORS.rst
sktalk-0.0.400.dist-info/LICENSE
sktalk-0.0.400.dist-info/METADATA
sktalk-0.0.400.dist-info/WHEEL
sktalk-0.0.400.dist-info/entry_points.txt
sktalk-0.0.400.dist-info/top_level.txt
sktalk-0.0.400.dist-info/RECORD
