Metadata-Version: 2.1
Name: sktalk
Version: 0.0.400
Summary: A Python package for processing real-world conversational speech data.
Home-page: https://github.com/liesenf/sktalk
Author: Andreas Liesenfeld
Author-email: lies0002@ntu.edu.sg
License: MIT license
Keywords: sktalk
Classifier: Development Status :: 2 - Pre-Alpha
Classifier: Intended Audience :: Developers
Classifier: License :: OSI Approved :: MIT License
Classifier: Natural Language :: English
Classifier: Programming Language :: Python :: 3
Classifier: Programming Language :: Python :: 3.6
Classifier: Programming Language :: Python :: 3.7
Classifier: Programming Language :: Python :: 3.8
Requires-Python: >=3.6
License-File: LICENSE
License-File: AUTHORS.rst
Requires-Dist: Click (>=7.0)
